{"took":73,"timed_out":false,"_shards":{"total":20,"successful":20,"failed":0},"hits":{"total":1657,"max_score":2.0771792,"hits":[{"_index":"dig-ht-california-ads-trial01-optimized","_type":"webpage","_id":"http://dig.isi.edu/ht/data/23342965/webpage","_score":2.0771792,"_source":{"description":["Lovely Bianca - 21\\n"]}},{"_index":"dig-ht-california-ads-trial01-optimized","_type":"webpage","_id":"http://dig.isi.edu/ht/data/23544958/webpage","_score":2.0771792,"_source":{"description":["$80 special Lovely Bianca $80 special - 21\\n"]}},{"_index":"dig-ht-california-ads-trial01-optimized","_type":"webpage","_id":"http://dig.isi.edu/ht/data/24028268/webpage","_score":2.0771792,"_source":{"description":["Lovely Bianca - 21\\n"]}},{"_index":"dig-ht-california-ads-trial01-optimized","_type":"webpage","_id":"http://dig.isi.edu/ht/data/25593796/webpage","_score":2.0771792,"_source":{"description":["Lovely Bianca - 21\\n"]}},{"_index":"dig-ht-california-ads-trial01-optimized","_type":"webpage","_id":"http://dig.isi.edu/ht/data/25674103/webpage","_score":2.0771792,"_source":{"description":["Lovely Bianca - 21\\n"]}},{"_index":"dig-ht-california-ads-trial01-optimized","_type":"webpage","_id":"http://dig.isi.edu/ht/data/25070842/webpage","_score":2.0771792,"_source":{"description":["Lovely Bianca - 21\\n"]}},{"_index":"dig-ht-california-ads-trial01-optimized","_type":"webpage","_id":"http://dig.isi.edu/ht/data/25731178/webpage","_score":2.0771792,"_source":{"description":["Lovely Bianca - 21\\n"]}},{"_index":"dig-ht-california-ads-trial01-optimized","_type":"webpage","_id":"http://dig.isi.edu/ht/data/66134824/webpage","_score":2.0771792,"_source":{"description":["sexy bianca is ready to play .. - 24\\n"]}},{"_index":"dig-ht-california-ads-trial01-optimized","_type":"webpage","_id":"http://dig.isi.edu/ht/data/24043746/webpage","_score":2.0675066,"_source":{"description":["Lovely Bianca - 21\\n"]}},{"_index":"dig-ht-california-ads-trial01-optimized","_type":"webpage","_id":"http://dig.isi.edu/ht/data/25635339/webpage","_score":2.0675066,"_source":{"description":["Lovely Bianca - 21\\n"]}},{"_index":"dig-ht-california-ads-trial01-optimized","_type":"webpage","_id":"http://dig.isi.edu/ht/data/73114969/webpage","_score":2.0675066,"_source":{"description":["Bianca New Arrival Busted DD  - 25\\n"]}},{"_index":"dig-ht-california-ads-trial01-optimized","_type":"webpage","_id":"http://dig.isi.edu/ht/data/23307544/webpage","_score":2.067175,"_source":{"description":["Bianca - 23\\n"]}},{"_index":"dig-ht-california-ads-trial01-optimized","_type":"webpage","_id":"http://dig.isi.edu/ht/data/23311028/webpage","_score":2.067175,"_source":{"description":["Lovely Bianca - 21\\n"]}},{"_index":"dig-ht-california-ads-trial01-optimized","_type":"webpage","_id":"http://dig.isi.edu/ht/data/23723412/webpage","_score":2.067175,"_source":{"description":["Lovely Bianca - 21\\n"]}},{"_index":"dig-ht-california-ads-trial01-optimized","_type":"webpage","_id":"http://dig.isi.edu/ht/data/23564774/webpage","_score":2.067175,"_source":{"description":["Lovely Bianca - 21\\n"]}},{"_index":"dig-ht-california-ads-trial01-optimized","_type":"webpage","_id":"http://dig.isi.edu/ht/data/24030955/webpage","_score":2.067175,"_source":{"description":["Lovely Bianca - 21\\n"]}},{"_index":"dig-ht-california-ads-trial01-optimized","_type":"webpage","_id":"http://dig.isi.edu/ht/data/25620630/webpage","_score":2.067175,"_source":{"description":["Lovely Bianca - 21\\n"]}},{"_index":"dig-ht-california-ads-trial01-optimized","_type":"webpage","_id":"http://dig.isi.edu/ht/data/74635296/webpage","_score":2.067175,"_source":{"description":["Bianca New Arrival Busted DD  - 25\\n"]}},{"_index":"dig-ht-california-ads-trial01-optimized","_type":"webpage","_id":"http://dig.isi.edu/ht/data/77428594/webpage","_score":2.067175,"_source":{"description":["Bianca New Arrival Busted DD  - 25\\n"]}},{"_index":"dig-ht-california-ads-trial01-optimized","_type":"webpage","_id":"http://dig.isi.edu/ht/data/69857182/webpage","_score":2.067175,"_source":{"description":["Bianca New Arrival Busted DD - 25\\n"]}},{"_index":"dig-ht-california-ads-trial01-optimized","_type":"webpage","_id":"http://dig.isi.edu/ht/data/23310928/webpage","_score":2.0641103,"_source":{"description":["Lovely Bianca - 21\\n"]}},{"_index":"dig-ht-california-ads-trial01-optimized","_type":"webpage","_id":"http://dig.isi.edu/ht/data/23309184/webpage","_score":2.0641103,"_source":{"description":["Lovely Bianca - 21\\n"]}},{"_index":"dig-ht-california-ads-trial01-optimized","_type":"webpage","_id":"http://dig.isi.edu/ht/data/23566978/webpage","_score":2.0641103,"_source":{"description":["Lovely Bianca - 21\\n"]}},{"_index":"dig-ht-california-ads-trial01-optimized","_type":"webpage","_id":"http://dig.isi.edu/ht/data/23739796/webpage","_score":2.0641103,"_source":{"description":["Bianca - 23\\n"]}},{"_index":"dig-ht-california-ads-trial01-optimized","_type":"webpage","_id":"http://dig.isi.edu/ht/data/23829734/webpage","_score":2.0641103,"_source":{"description":["Lovely Bianca - 21\\n"]}},{"_index":"dig-ht-california-ads-trial01-optimized","_type":"webpage","_id":"http://dig.isi.edu/ht/data/26345156/webpage","_score":2.0641103,"_source":{"description":["Bianca - 23\\n"]}},{"_index":"dig-ht-california-ads-trial01-optimized","_type":"webpage","_id":"http://dig.isi.edu/ht/data/25635346/webpage","_score":2.0641103,"_source":{"description":["Lovely Bianca - 21\\n"]}},{"_index":"dig-ht-california-ads-trial01-optimized","_type":"webpage","_id":"http://dig.isi.edu/ht/data/66313621/webpage","_score":2.0641103,"_source":{"description":["Bianca Limited Time Only!!! 100%Latina - 23\\n"]}},{"_index":"dig-ht-california-ads-trial01-optimized","_type":"webpage","_id":"http://dig.isi.edu/ht/data/68928410/webpage","_score":2.0641103,"_source":{"description":["Bianca New Arrival Busted DD - 25\\n"]}},{"_index":"dig-ht-california-ads-trial01-optimized","_type":"webpage","_id":"http://dig.isi.edu/ht/data/74383380/webpage","_score":2.0641103,"_source":{"description":["Bianca New Arrival Busted DD  - 25\\n"]}},{"_index":"dig-ht-california-ads-trial01-optimized","_type":"webpage","_id":"http://dig.isi.edu/ht/data/23566976/webpage","_score":2.0609722,"_source":{"description":["$80 special Lovely Bianca $80 special - 21\\n"]}},{"_index":"dig-ht-california-ads-trial01-optimized","_type":"webpage","_id":"http://dig.isi.edu/ht/data/23743564/webpage","_score":2.0609722,"_source":{"description":["$80 special Lovely Bianca $80 special - 21\\n"]}},{"_index":"dig-ht-california-ads-trial01-optimized","_type":"webpage","_id":"http://dig.isi.edu/ht/data/24554222/webpage","_score":2.0609722,"_source":{"description":["Lovely Bianca - 21\\n"]}},{"_index":"dig-ht-california-ads-trial01-optimized","_type":"webpage","_id":"http://dig.isi.edu/ht/data/35216913/webpage","_score":2.0609722,"_source":{"description":["***MISS.PUERTO RICO*** Busty Bianca *** $70 Special :) - 21\\n"]}},{"_index":"dig-ht-california-ads-trial01-optimized","_type":"webpage","_id":"http://dig.isi.edu/ht/data/24561032/webpage","_score":2.0609095,"_source":{"description":["Lovely Bianca - 21\\n"]}},{"_index":"dig-ht-california-ads-trial01-optimized","_type":"webpage","_id":"http://dig.isi.edu/ht/data/76386009/webpage","_score":2.0609095,"_source":{"description":["Bianca New Arrival Busted DD  - 25\\n"]}},{"_index":"dig-ht-california-ads-trial01-optimized","_type":"webpage","_id":"http://dig.isi.edu/ht/data/25620628/webpage","_score":2.058209,"_source":{"description":["Lovely Bianca - 21\\n"]}},{"_index":"dig-ht-california-ads-trial01-optimized","_type":"webpage","_id":"http://dig.isi.edu/ht/data/23548238/webpage","_score":2.058209,"_source":{"description":["Lovely Bianca - 21\\n"]}},{"_index":"dig-ht-california-ads-trial01-optimized","_type":"webpage","_id":"http://dig.isi.edu/ht/data/23547585/webpage","_score":2.058209,"_source":{"description":["Lovely Bianca - 21\\n"]}},{"_index":"dig-ht-california-ads-trial01-optimized","_type":"webpage","_id":"http://dig.isi.edu/ht/data/23743561/webpage","_score":2.058209,"_source":{"description":["Lovely Bianca - 21\\n"]}},{"_index":"dig-ht-california-ads-trial01-optimized","_type":"webpage","_id":"http://dig.isi.edu/ht/data/23550767/webpage","_score":2.058209,"_source":{"description":["$80 special Lovely Bianca $80 special - 21\\n"]}},{"_index":"dig-ht-california-ads-trial01-optimized","_type":"webpage","_id":"http://dig.isi.edu/ht/data/24553776/webpage","_score":2.058209,"_source":{"description":["Lovely Bianca - 21\\n"]}},{"_index":"dig-ht-california-ads-trial01-optimized","_type":"webpage","_id":"http://dig.isi.edu/ht/data/77131251/webpage","_score":2.058209,"_source":{"description":["Bianca New Arrival Busted DD 6692349637 - 25\\n"]}},{"_index":"dig-ht-california-ads-trial01-optimized","_type":"webpage","_id":"http://dig.isi.edu/ht/data/77181159/webpage","_score":2.058209,"_source":{"description":["Bianca New Arrival Busted DD 6692349637 - 25\\n"]}},{"_index":"dig-ht-california-ads-trial01-optimized","_type":"webpage","_id":"http://dig.isi.edu/ht/data/25592419/webpage","_score":2.0526137,"_source":{"description":["Lovely Bianca - 21\\n"]}},{"_index":"dig-ht-california-ads-trial01-optimized","_type":"webpage","_id":"http://dig.isi.edu/ht/data/25630175/webpage","_score":2.0526137,"_source":{"description":["Lovely Bianca - 21\\n"]}},{"_index":"dig-ht-california-ads-trial01-optimized","_type":"webpage","_id":"http://dig.isi.edu/ht/data/25683089/webpage","_score":2.0526137,"_source":{"description":["Lovely Bianca - 21\\n"]}},{"_index":"dig-ht-california-ads-trial01-optimized","_type":"webpage","_id":"http://dig.isi.edu/ht/data/31272064/webpage","_score":2.0526137,"_source":{"description":["Bianca Monrow (San Francisco In call $140) 30 Min - 28\\n"]}},{"_index":"dig-ht-california-ads-trial01-optimized","_type":"webpage","_id":"http://dig.isi.edu/ht/data/23339876/webpage","_score":2.0526137,"_source":{"description":["Bianca - 23\\n"]}},{"_index":"dig-ht-california-ads-trial01-optimized","_type":"webpage","_id":"http://dig.isi.edu/ht/data/23356189/webpage","_score":2.0526137,"_source":{"description":["Lovely Bianca - 21\\n"]}},{"_index":"dig-ht-california-ads-trial01-optimized","_type":"webpage","_id":"http://dig.isi.edu/ht/data/23569268/webpage","_score":2.0526137,"_source":{"description":["$80 special Lovely Bianca $80 special - 21\\n"]}},{"_index":"dig-ht-california-ads-trial01-optimized","_type":"webpage","_id":"http://dig.isi.edu/ht/data/24554122/webpage","_score":2.0526137,"_source":{"description":["Lovely Bianca - 21\\n"]}},{"_index":"dig-ht-california-ads-trial01-optimized","_type":"webpage","_id":"http://dig.isi.edu/ht/data/24578276/webpage","_score":2.0526137,"_source":{"description":["Carpe Diem \\u2013 Sexy Classy Upscale Beauty Bianca Monrow - 28\\n"]}},{"_index":"dig-ht-california-ads-trial01-optimized","_type":"webpage","_id":"http://dig.isi.edu/ht/data/72252384/webpage","_score":2.0526137,"_source":{"description":["Bianca New Arrival Busted DD  - 25\\n"]}},{"_index":"dig-ht-california-ads-trial01-optimized","_type":"webpage","_id":"http://dig.isi.edu/ht/data/70744227/webpage","_score":2.0526137,"_source":{"description":["Bianca New Arrival Busted DD - 25\\n"]}},{"_index":"dig-ht-california-ads-trial01-optimized","_type":"webpage","_id":"http://dig.isi.edu/ht/data/73572841/webpage","_score":2.0526137,"_source":{"description":["Bianca New Arrival Busted DD  - 25\\n"]}},{"_index":"dig-ht-california-ads-trial01-optimized","_type":"webpage","_id":"http://dig.isi.edu/ht/data/74206730/webpage","_score":2.0492177,"_source":{"description":["Bianca New Arrival Busted DD  - 25\\n"]}},{"_index":"dig-ht-california-ads-trial01-optimized","_type":"webpage","_id":"http://dig.isi.edu/ht/data/23748669/webpage","_score":2.0492177,"_source":{"description":["Lovely Bianca - 21\\n"]}},{"_index":"dig-ht-california-ads-trial01-optimized","_type":"webpage","_id":"http://dig.isi.edu/ht/data/23748670/webpage","_score":2.0492177,"_source":{"description":["$80 special Lovely Bianca $80 special - 21\\n"]}},{"_index":"dig-ht-california-ads-trial01-optimized","_type":"webpage","_id":"http://dig.isi.edu/ht/data/24026298/webpage","_score":2.0492177,"_source":{"description":["Bianca - 23\\n"]}},{"_index":"dig-ht-california-ads-trial01-optimized","_type":"webpage","_id":"http://dig.isi.edu/ht/data/24550935/webpage","_score":2.0492177,"_source":{"description":["Bianca - 23\\n"]}},{"_index":"dig-ht-california-ads-trial01-optimized","_type":"webpage","_id":"http://dig.isi.edu/ht/data/60785111/webpage","_score":2.0492177,"_source":{"description":["Bianca Hour Glass Frame - 19\\n"]}},{"_index":"dig-ht-california-ads-trial01-optimized","_type":"webpage","_id":"http://dig.isi.edu/ht/data/76596790/webpage","_score":2.0492177,"_source":{"description":["Bianca New Arrival Busted DD 6692349637 - 25\\n"]}},{"_index":"dig-ht-california-ads-trial01-optimized","_type":"webpage","_id":"http://dig.isi.edu/ht/data/25596284/webpage","_score":2.0492177,"_source":{"description":["Lovely Bianca - 21\\n"]}},{"_index":"dig-ht-california-ads-trial01-optimized","_type":"webpage","_id":"http://dig.isi.edu/ht/data/57486723/webpage","_score":2.0454347,"_source":{"description":["New to town bianca - 19\\n"]}},{"_index":"dig-ht-california-ads-trial01-optimized","_type":"webpage","_id":"http://dig.isi.edu/ht/data/71480747/webpage","_score":2.0454347,"_source":{"description":["Bianca New Arrival Busted DD  - 25\\n"]}},{"_index":"dig-ht-california-ads-trial01-optimized","_type":"webpage","_id":"http://dig.isi.edu/ht/data/62419592/webpage","_score":2.0454347,"_source":{"description":["Bianca California Sweetheart - 19\\n"]}},{"_index":"dig-ht-california-ads-trial01-optimized","_type":"webpage","_id":"http://dig.isi.edu/ht/data/23343634/webpage","_score":2.0454347,"_source":{"description":["Lovely Bianca - 21\\n"]}},{"_index":"dig-ht-california-ads-trial01-optimized","_type":"webpage","_id":"http://dig.isi.edu/ht/data/25593783/webpage","_score":2.0454347,"_source":{"description":["Lovely Bianca - 21\\n"]}},{"_index":"dig-ht-california-ads-trial01-optimized","_type":"webpage","_id":"http://dig.isi.edu/ht/data/25587621/webpage","_score":2.0454347,"_source":{"description":["Lovely Bianca - 21\\n"]}},{"_index":"dig-ht-california-ads-trial01-optimized","_type":"webpage","_id":"http://dig.isi.edu/ht/data/77166801/webpage","_score":2.0454347,"_source":{"description":["Bianca New Arrival Busted DD 6692349637 - 25\\n"]}},{"_index":"dig-ht-california-ads-trial01-optimized","_type":"webpage","_id":"http://dig.isi.edu/ht/data/25604716/webpage","_score":2.0453384,"_source":{"description":["Lovely Bianca - 21\\n"]}},{"_index":"dig-ht-california-ads-trial01-optimized","_type":"webpage","_id":"http://dig.isi.edu/ht/data/25626468/webpage","_score":2.0453384,"_source":{"description":["Lovely Bianca - 21\\n"]}},{"_index":"dig-ht-california-ads-trial01-optimized","_type":"webpage","_id":"http://dig.isi.edu/ht/data/23311373/webpage","_score":2.0453384,"_source":{"description":["Lovely Bianca - 21\\n"]}},{"_index":"dig-ht-california-ads-trial01-optimized","_type":"webpage","_id":"http://dig.isi.edu/ht/data/23569266/webpage","_score":2.0453384,"_source":{"description":["Lovely Bianca - 21\\n"]}},{"_index":"dig-ht-california-ads-trial01-optimized","_type":"webpage","_id":"http://dig.isi.edu/ht/data/23727064/webpage","_score":2.0453384,"_source":{"description":["Lovely Bianca - 21\\n"]}},{"_index":"dig-ht-california-ads-trial01-optimized","_type":"webpage","_id":"http://dig.isi.edu/ht/data/73098251/webpage","_score":2.0453384,"_source":{"description":["Bianca New Arrival Busted DD  - 25\\n"]}},{"_index":"dig-ht-california-ads-trial01-optimized","_type":"webpage","_id":"http://dig.isi.edu/ht/data/23310480/webpage","_score":2.0453348,"_source":{"description":["$80 special Lovely Bianca $80 special - 21\\n"]}},{"_index":"dig-ht-california-ads-trial01-optimized","_type":"webpage","_id":"http://dig.isi.edu/ht/data/23547587/webpage","_score":2.0453348,"_source":{"description":["$80 special Lovely Bianca $80 special - 21\\n"]}},{"_index":"dig-ht-california-ads-trial01-optimized","_type":"webpage","_id":"http://dig.isi.edu/ht/data/24030790/webpage","_score":2.0453348,"_source":{"description":["Lovely Bianca - 21\\n"]}},{"_index":"dig-ht-california-ads-trial01-optimized","_type":"webpage","_id":"http://dig.isi.edu/ht/data/24554359/webpage","_score":2.0453348,"_source":{"description":["Lovely Bianca - 21\\n"]}},{"_index":"dig-ht-california-ads-trial01-optimized","_type":"webpage","_id":"http://dig.isi.edu/ht/data/24043987/webpage","_score":2.0453348,"_source":{"description":["Lovely Bianca - 21\\n"]}},{"_index":"dig-ht-california-ads-trial01-optimized","_type":"webpage","_id":"http://dig.isi.edu/ht/data/25717425/webpage","_score":2.0453348,"_source":{"description":["Lovely Bianca - 21\\n"]}},{"_index":"dig-ht-california-ads-trial01-optimized","_type":"webpage","_id":"http://dig.isi.edu/ht/data/74357281/webpage","_score":2.0453348,"_source":{"description":["Bianca New Arrival Busted DD  - 25\\n"]}},{"_index":"dig-ht-california-ads-trial01-optimized","_type":"webpage","_id":"http://dig.isi.edu/ht/data/69338427/webpage","_score":2.0433466,"_source":{"description":["bianca - (818)855-3662 - 22\\n"]}},{"_index":"dig-ht-california-ads-trial01-optimized","_type":"webpage","_id":"http://dig.isi.edu/ht/data/69091168/webpage","_score":2.0433466,"_source":{"description":["Bianca New Arrival Busted DD - 25\\n"]}},{"_index":"dig-ht-california-ads-trial01-optimized","_type":"webpage","_id":"http://dig.isi.edu/ht/data/57277709/webpage","_score":2.0433466,"_source":{"description":["Bianca hot and ready now. - 24\\n"]}},{"_index":"dig-ht-california-ads-trial01-optimized","_type":"webpage","_id":"http://dig.isi.edu/ht/data/77166788/webpage","_score":2.0433466,"_source":{"description":["Bianca New Arrival Busted DD 6692349637 - 25\\n"]}},{"_index":"dig-ht-california-ads-trial01-optimized","_type":"webpage","_id":"http://dig.isi.edu/ht/data/23310568/webpage","_score":2.0433466,"_source":{"description":["Lovely Bianca - 21\\n"]}},{"_index":"dig-ht-california-ads-trial01-optimized","_type":"webpage","_id":"http://dig.isi.edu/ht/data/23343377/webpage","_score":2.0433466,"_source":{"description":["Lovely Bianca - 21\\n"]}},{"_index":"dig-ht-california-ads-trial01-optimized","_type":"webpage","_id":"http://dig.isi.edu/ht/data/23341517/webpage","_score":2.0433466,"_source":{"description":["Lovely Bianca - 21\\n"]}},{"_index":"dig-ht-california-ads-trial01-optimized","_type":"webpage","_id":"http://dig.isi.edu/ht/data/23548235/webpage","_score":2.0433466,"_source":{"description":["$80 special Lovely Bianca $80 special - 21\\n"]}},{"_index":"dig-ht-california-ads-trial01-optimized","_type":"webpage","_id":"http://dig.isi.edu/ht/data/23730070/webpage","_score":2.0433466,"_source":{"description":["Lovely Bianca - 21\\n"]}},{"_index":"dig-ht-california-ads-trial01-optimized","_type":"webpage","_id":"http://dig.isi.edu/ht/data/23815953/webpage","_score":2.0433466,"_source":{"description":["Lovely Bianca - 21\\n"]}},{"_index":"dig-ht-california-ads-trial01-optimized","_type":"webpage","_id":"http://dig.isi.edu/ht/data/24030658/webpage","_score":2.0433466,"_source":{"description":["Lovely Bianca - 21\\n"]}},{"_index":"dig-ht-california-ads-trial01-optimized","_type":"webpage","_id":"http://dig.isi.edu/ht/data/25080092/webpage","_score":2.0433466,"_source":{"description":["Lovely Bianca - 21\\n"]}},{"_index":"dig-ht-california-ads-trial01-optimized","_type":"webpage","_id":"http://dig.isi.edu/ht/data/25598252/webpage","_score":2.0433466,"_source":{"description":["Lovely Bianca - 21\\n"]}},{"_index":"dig-ht-california-ads-trial01-optimized","_type":"webpage","_id":"http://dig.isi.edu/ht/data/25731482/webpage","_score":2.0433466,"_source":{"description":["Lovely Bianca - 21\\n"]}},{"_index":"dig-ht-california-ads-trial01-optimized","_type":"webpage","_id":"http://dig.isi.edu/ht/data/72011453/webpage","_score":2.043021,"_source":{"description":["Bianca New Arrival Busted DD  - 25\\n"]}},{"_index":"dig-ht-california-ads-trial01-optimized","_type":"webpage","_id":"http://dig.isi.edu/ht/data/26724815/webpage","_score":2.043021,"_source":{"description":["Bianca - 23\\n"]}},{"_index":"dig-ht-california-ads-trial01-optimized","_type":"webpage","_id":"http://dig.isi.edu/ht/data/23343493/webpage","_score":2.043021,"_source":{"description":["Lovely Bianca - 21\\n"]}},{"_index":"dig-ht-california-ads-trial01-optimized","_type":"webpage","_id":"http://dig.isi.edu/ht/data/25069399/webpage","_score":2.043021,"_source":{"description":["Lovely Bianca - 21\\n"]}},{"_index":"dig-ht-california-ads-trial01-optimized","_type":"webpage","_id":"http://dig.isi.edu/ht/data/35243666/webpage","_score":2.043021,"_source":{"description":["***MISS.PUERTO RICO*** Busty Bianca *** $60 Special :) - 21\\n"]}},{"_index":"dig-ht-california-ads-trial01-optimized","_type":"webpage","_id":"http://dig.isi.edu/ht/data/70494162/webpage","_score":2.0428603,"_source":{"description":["Bianca New Arrival Busted DD - 25\\n"]}},{"_index":"dig-ht-california-ads-trial01-optimized","_type":"webpage","_id":"http://dig.isi.edu/ht/data/23544959/webpage","_score":2.0428603,"_source":{"description":["Lovely Bianca - 21\\n"]}},{"_index":"dig-ht-california-ads-trial01-optimized","_type":"webpage","_id":"http://dig.isi.edu/ht/data/23732745/webpage","_score":2.0428603,"_source":{"description":["$80 special Lovely Bianca $80 special - 21\\n"]}},{"_index":"dig-ht-california-ads-trial01-optimized","_type":"webpage","_id":"http://dig.isi.edu/ht/data/23730064/webpage","_score":2.0428603,"_source":{"description":["$80 special Lovely Bianca $80 special - 21\\n"]}},{"_index":"dig-ht-california-ads-trial01-optimized","_type":"webpage","_id":"http://dig.isi.edu/ht/data/23723408/webpage","_score":2.0428603,"_source":{"description":["$80 special Lovely Bianca $80 special - 21\\n"]}},{"_index":"dig-ht-california-ads-trial01-optimized","_type":"webpage","_id":"http://dig.isi.edu/ht/data/24552469/webpage","_score":2.0428603,"_source":{"description":["Lovely Bianca - 21\\n"]}},{"_index":"dig-ht-california-ads-trial01-optimized","_type":"webpage","_id":"http://dig.isi.edu/ht/data/48616943/webpage","_score":2.0428603,"_source":{"description":["PornStar ..BIANCA Up All Night  - 20\\n"]}},{"_index":"dig-ht-california-ads-trial01-optimized","_type":"webpage","_id":"http://dig.isi.edu/ht/data/61324100/webpage","_score":2.0428603,"_source":{"description":["Bianca 38DD New Number - 19\\n"]}},{"_index":"dig-ht-california-ads-trial01-optimized","_type":"webpage","_id":"http://dig.isi.edu/ht/data/23342870/webpage","_score":2.0388415,"_source":{"description":["$80 special Lovely Bianca $80 special - 21\\n"]}},{"_index":"dig-ht-california-ads-trial01-optimized","_type":"webpage","_id":"http://dig.isi.edu/ht/data/23355977/webpage","_score":2.0388415,"_source":{"description":["Lovely Bianca - 21\\n"]}},{"_index":"dig-ht-california-ads-trial01-optimized","_type":"webpage","_id":"http://dig.isi.edu/ht/data/23725697/webpage","_score":2.0388415,"_source":{"description":["Lovely Bianca - 21\\n"]}},{"_index":"dig-ht-california-ads-trial01-optimized","_type":"webpage","_id":"http://dig.isi.edu/ht/data/23567842/webpage","_score":2.0388415,"_source":{"description":["Lovely Bianca - 21\\n"]}},{"_index":"dig-ht-california-ads-trial01-optimized","_type":"webpage","_id":"http://dig.isi.edu/ht/data/23732736/webpage","_score":2.0388415,"_source":{"description":["Lovely Bianca - 21\\n"]}},{"_index":"dig-ht-california-ads-trial01-optimized","_type":"webpage","_id":"http://dig.isi.edu/ht/data/24031164/webpage","_score":2.0388415,"_source":{"description":["Lovely Bianca - 21\\n"]}},{"_index":"dig-ht-california-ads-trial01-optimized","_type":"webpage","_id":"http://dig.isi.edu/ht/data/24561209/webpage","_score":2.0388415,"_source":{"description":["Lovely Bianca - 21\\n"]}},{"_index":"dig-ht-california-ads-trial01-optimized","_type":"webpage","_id":"http://dig.isi.edu/ht/data/25587622/webpage","_score":2.0388415,"_source":{"description":["Lovely Bianca - 21\\n"]}},{"_index":"dig-ht-california-ads-trial01-optimized","_type":"webpage","_id":"http://dig.isi.edu/ht/data/25100234/webpage","_score":2.0388415,"_source":{"description":["Carpe Diem \\u2013 Sexy Classy Upscale Beauty Bianca Monrow - 28\\n"]}},{"_index":"dig-ht-california-ads-trial01-optimized","_type":"webpage","_id":"http://dig.isi.edu/ht/data/77255403/webpage","_score":2.0388415,"_source":{"description":["Bianca New Arrival Busted DD 6692349637 - 25\\n"]}},{"_index":"dig-ht-california-ads-trial01-optimized","_type":"webpage","_id":"http://dig.isi.edu/ht/data/23311163/webpage","_score":2.0373063,"_source":{"description":["Lovely Bianca - 21\\n"]}},{"_index":"dig-ht-california-ads-trial01-optimized","_type":"webpage","_id":"http://dig.isi.edu/ht/data/23550771/webpage","_score":2.0373063,"_source":{"description":["Lovely Bianca - 21\\n"]}},{"_index":"dig-ht-california-ads-trial01-optimized","_type":"webpage","_id":"http://dig.isi.edu/ht/data/23750162/webpage","_score":2.0373063,"_source":{"description":["$80 special Lovely Bianca $80 special - 21\\n"]}},{"_index":"dig-ht-california-ads-trial01-optimized","_type":"webpage","_id":"http://dig.isi.edu/ht/data/25067716/webpage","_score":2.0373063,"_source":{"description":["Bianca - 23\\n"]}},{"_index":"dig-ht-california-ads-trial01-optimized","_type":"webpage","_id":"http://dig.isi.edu/ht/data/25630163/webpage","_score":2.0373063,"_source":{"description":["Lovely Bianca - 21\\n"]}},{"_index":"dig-ht-california-ads-trial01-optimized","_type":"webpage","_id":"http://dig.isi.edu/ht/data/25604722/webpage","_score":2.0373063,"_source":{"description":["Lovely Bianca - 21\\n"]}},{"_index":"dig-ht-california-ads-trial01-optimized","_type":"webpage","_id":"http://dig.isi.edu/ht/data/25598256/webpage","_score":2.0373063,"_source":{"description":["Lovely Bianca - 21\\n"]}},{"_index":"dig-ht-california-ads-trial01-optimized","_type":"webpage","_id":"http://dig.isi.edu/ht/data/25621297/webpage","_score":2.0373063,"_source":{"description":["Lovely Bianca - 21\\n"]}},{"_index":"dig-ht-california-ads-trial01-optimized","_type":"webpage","_id":"http://dig.isi.edu/ht/data/25672761/webpage","_score":2.0373063,"_source":{"description":["Bianca - 23\\n"]}},{"_index":"dig-ht-california-ads-trial01-optimized","_type":"webpage","_id":"http://dig.isi.edu/ht/data/25079920/webpage","_score":2.0373063,"_source":{"description":["Lovely Bianca - 21\\n"]}},{"_index":"dig-ht-california-ads-trial01-optimized","_type":"webpage","_id":"http://dig.isi.edu/ht/data/27993662/webpage","_score":2.0373063,"_source":{"description":["Bianca - 23\\n"]}},{"_index":"dig-ht-california-ads-trial01-optimized","_type":"webpage","_id":"http://dig.isi.edu/ht/data/73798075/webpage","_score":2.0373063,"_source":{"description":["Bianca New Arrival Busted DD  - 25\\n"]}},{"_index":"dig-ht-california-ads-trial01-optimized","_type":"webpage","_id":"http://dig.isi.edu/ht/data/75846327/webpage","_score":2.0373063,"_source":{"description":["Bianca New Arrival Busted DD  - 25\\n"]}},{"_index":"dig-ht-california-ads-trial01-optimized","_type":"webpage","_id":"http://dig.isi.edu/ht/data/74707614/webpage","_score":2.0340884,"_source":{"description":["Bianca New Arrival Busted DD  - 25\\n"]}},{"_index":"dig-ht-california-ads-trial01-optimized","_type":"webpage","_id":"http://dig.isi.edu/ht/data/73880859/webpage","_score":2.0340884,"_source":{"description":["Bianca New Arrival Busted DD  - 25\\n"]}},{"_index":"dig-ht-california-ads-trial01-optimized","_type":"webpage","_id":"http://dig.isi.edu/ht/data/66336316/webpage","_score":2.0340884,"_source":{"description":["Ts Bianca & Ts josilyn - 954EIGHT30THREE125 - 24\\n"]}},{"_index":"dig-ht-california-ads-trial01-optimized","_type":"webpage","_id":"http://dig.isi.edu/ht/data/23343850/webpage","_score":2.0340884,"_source":{"description":["Lovely Bianca - 21\\n"]}},{"_index":"dig-ht-california-ads-trial01-optimized","_type":"webpage","_id":"http://dig.isi.edu/ht/data/23549650/webpage","_score":2.0340884,"_source":{"description":["$80 special Lovely Bianca $80 special - 21\\n"]}},{"_index":"dig-ht-california-ads-trial01-optimized","_type":"webpage","_id":"http://dig.isi.edu/ht/data/23549649/webpage","_score":2.0340884,"_source":{"description":["Lovely Bianca - 21\\n"]}},{"_index":"dig-ht-california-ads-trial01-optimized","_type":"webpage","_id":"http://dig.isi.edu/ht/data/23553859/webpage","_score":2.0340884,"_source":{"description":["$80 special Lovely Bianca $80 special - 21\\n"]}},{"_index":"dig-ht-california-ads-trial01-optimized","_type":"webpage","_id":"http://dig.isi.edu/ht/data/23562563/webpage","_score":2.0340884,"_source":{"description":["Bianca - 23\\n"]}},{"_index":"dig-ht-california-ads-trial01-optimized","_type":"webpage","_id":"http://dig.isi.edu/ht/data/23750164/webpage","_score":2.0340884,"_source":{"description":["Lovely Bianca - 21\\n"]}},{"_index":"dig-ht-california-ads-trial01-optimized","_type":"webpage","_id":"http://dig.isi.edu/ht/data/25592421/webpage","_score":2.0340884,"_source":{"description":["Lovely Bianca - 21\\n"]}},{"_index":"dig-ht-california-ads-trial01-optimized","_type":"webpage","_id":"http://dig.isi.edu/ht/data/25624278/webpage","_score":2.0340884,"_source":{"description":["Lovely Bianca - 21\\n"]}},{"_index":"dig-ht-california-ads-trial01-optimized","_type":"webpage","_id":"http://dig.isi.edu/ht/data/25683235/webpage","_score":2.0340884,"_source":{"description":["Lovely Bianca - 21\\n"]}},{"_index":"dig-ht-california-ads-trial01-optimized","_type":"webpage","_id":"http://dig.isi.edu/ht/data/25596292/webpage","_score":2.0340884,"_source":{"description":["Lovely Bianca - 21\\n"]}},{"_index":"dig-ht-california-ads-trial01-optimized","_type":"webpage","_id":"http://dig.isi.edu/ht/data/46152293/webpage","_score":2.0340884,"_source":{"description":["Bianca Loves - 21\\n"]}},{"_index":"dig-ht-california-ads-trial01-optimized","_type":"webpage","_id":"http://dig.isi.edu/ht/data/61908659/webpage","_score":2.0340884,"_source":{"description":["Bianca Hour Glass Frame - 19\\n"]}},{"_index":"dig-ht-california-ads-trial01-optimized","_type":"webpage","_id":"http://dig.isi.edu/ht/data/61538715/webpage","_score":2.0340884,"_source":{"description":["Bianca Hour Glass Frame - 19\\n"]}},{"_index":"dig-ht-california-ads-trial01-optimized","_type":"webpage","_id":"http://dig.isi.edu/ht/data/25716019/webpage","_score":2.0292017,"_source":{"description":["Bianca - 23\\n"]}},{"_index":"dig-ht-california-ads-trial01-optimized","_type":"webpage","_id":"http://dig.isi.edu/ht/data/45777063/webpage","_score":2.0292017,"_source":{"description":["Bianca $150 Special - 21\\n"]}},{"_index":"dig-ht-california-ads-trial01-optimized","_type":"webpage","_id":"http://dig.isi.edu/ht/data/62259407/webpage","_score":2.0292017,"_source":{"description":["Bianca \\u2764Hourglass Frame - 19\\n"]}},{"_index":"dig-ht-california-ads-trial01-optimized","_type":"webpage","_id":"http://dig.isi.edu/ht/data/23553863/webpage","_score":2.0292017,"_source":{"description":["Lovely Bianca - 21\\n"]}},{"_index":"dig-ht-california-ads-trial01-optimized","_type":"webpage","_id":"http://dig.isi.edu/ht/data/23567840/webpage","_score":2.0292017,"_source":{"description":["$80 special Lovely Bianca $80 special - 21\\n"]}},{"_index":"dig-ht-california-ads-trial01-optimized","_type":"webpage","_id":"http://dig.isi.edu/ht/data/23727068/webpage","_score":2.0292017,"_source":{"description":["$80 special Lovely Bianca $80 special - 21\\n"]}},{"_index":"dig-ht-california-ads-trial01-optimized","_type":"webpage","_id":"http://dig.isi.edu/ht/data/23565279/webpage","_score":2.0292017,"_source":{"description":["Lovely Bianca - 21\\n"]}},{"_index":"dig-ht-california-ads-trial01-optimized","_type":"webpage","_id":"http://dig.isi.edu/ht/data/25070720/webpage","_score":2.0292017,"_source":{"description":["$80 special Lovely Bianca $80 special - 21\\n"]}},{"_index":"dig-ht-california-ads-trial01-optimized","_type":"webpage","_id":"http://dig.isi.edu/ht/data/76337535/webpage","_score":2.0292017,"_source":{"description":["Bianca New Arrival Busted DD  - 25\\n"]}},{"_index":"dig-ht-california-ads-trial01-optimized","_type":"webpage","_id":"http://dig.isi.edu/ht/data/77255382/webpage","_score":2.0292017,"_source":{"description":["Bianca New Arrival Busted DD 6692349637 - 25\\n"]}},{"_index":"dig-ht-california-ads-trial01-optimized","_type":"webpage","_id":"http://dig.isi.edu/ht/data/23570999/webpage","_score":2.0276566,"_source":{"description":["$80 special Lovely Bianca $80 special - 21\\n"]}},{"_index":"dig-ht-california-ads-trial01-optimized","_type":"webpage","_id":"http://dig.isi.edu/ht/data/23571000/webpage","_score":2.0276566,"_source":{"description":["Lovely Bianca - 21\\n"]}},{"_index":"dig-ht-california-ads-trial01-optimized","_type":"webpage","_id":"http://dig.isi.edu/ht/data/23725700/webpage","_score":2.0276566,"_source":{"description":["$80 special Lovely Bianca $80 special - 21\\n"]}},{"_index":"dig-ht-california-ads-trial01-optimized","_type":"webpage","_id":"http://dig.isi.edu/ht/data/23828085/webpage","_score":2.0276566,"_source":{"description":["Lovely Bianca - 21\\n"]}},{"_index":"dig-ht-california-ads-trial01-optimized","_type":"webpage","_id":"http://dig.isi.edu/ht/data/24554532/webpage","_score":2.0276566,"_source":{"description":["Lovely Bianca - 21\\n"]}},{"_index":"dig-ht-california-ads-trial01-optimized","_type":"webpage","_id":"http://dig.isi.edu/ht/data/46531760/webpage","_score":2.0276566,"_source":{"description":["sexy thick Bianca upscale fun !! Specials - 22\\n"]}},{"_index":"dig-ht-california-ads-trial01-optimized","_type":"webpage","_id":"http://dig.isi.edu/ht/data/74166369/webpage","_score":2.0276566,"_source":{"description":["Bianca New Arrival Busted DD  - 25\\n"]}},{"_index":"dig-ht-california-ads-trial01-optimized","_type":"webpage","_id":"http://dig.isi.edu/ht/data/801303/webpage","_score":2.0224874,"_source":{"description":["Hot body face n tits just came in last night.  Ready to fullfill all of your needs and fantasies.  Im that one very open minded.!!!    NO RUSH JOB VERY DISCREET<br>\\n<br>\\n<br>\\n<br>\\n      CAll bianca at 916-640-4292     IN/OUT calls  24/7  XOXOXOS Bianca\\n"]}},{"_index":"dig-ht-california-ads-trial01-optimized","_type":"webpage","_id":"http://dig.isi.edu/ht/data/36484995/webpage","_score":2.0168304,"_source":{"description":["Hot body face n tits just came in last night.  Ready to fullfill all of your needs and fantasies.  Im that one very open minded.!!!    NO RUSH JOB VERY DISCREET<br>\\n<br>\\n<br>\\n<br>\\n      CAll bianca at 916-640-4292     IN/OUT calls  24/7  XOXOXOS Bianca\\n"]}},{"_index":"dig-ht-california-ads-trial01-optimized","_type":"webpage","_id":"http://dig.isi.edu/ht/data/22836352/webpage","_score":2.0017433,"_source":{"description":["standing @ 5'2 135lbs<br>\\navailable for INCALL ONLY! <br>\\n<br>\\n55&DYER<br>\\n<br>\\n60qv<br>\\n120hh<br>\\n180h <br>\\n<br>\\n*No extra pictures *No Email <br>\\nCall/Txt Bianca @ 424-261-3305\\n"]}},{"_index":"dig-ht-california-ads-trial01-optimized","_type":"webpage","_id":"http://dig.isi.edu/ht/data/39250793/webpage","_score":1.9929914,"_source":{"description":["standing @ 5'2 135lbs<br>\\navailable for INCALL ONLY! <br>\\n<br>\\n55&DYER<br>\\n<br>\\n60qv<br>\\n120hh<br>\\n180h <br>\\n<br>\\n*No extra pictures *No Email <br>\\nCall/Txt Bianca @ 424-261-3305\\n"]}},{"_index":"dig-ht-california-ads-trial01-optimized","_type":"webpage","_id":"http://dig.isi.edu/ht/data/60823331/webpage","_score":1.7808101,"_source":{"description":["Hey fellas , my name Bianca . I'm a 19 year old Cali girl with a winning personality . My pictures are 100% real and  I take very good care of my body and hygiene . My smile is garaunteed to make you smile . I'll promise to keep you satisfied and keep you coming back for more ? 209-597-4262\\n"]}},{"_index":"dig-ht-california-ads-trial01-optimized","_type":"webpage","_id":"http://dig.isi.edu/ht/data/77729890/webpage","_score":1.7597499,"_source":{"description":["10am-11PM<br>\\n<br>\\n160hour, 120 half hour<br>\\n<br>\\nIf you haven't seen Bianca You don't know what is love.<br>\\nShe is excellent worker Kiss, Hugs and a lots more<br>\\nCall Sexy PO 669-234-9637 <br>\\n<br>\\n<br>\\nLocation: ELAN VILLAGE\\n"]}},{"_index":"dig-ht-california-ads-trial01-optimized","_type":"webpage","_id":"http://dig.isi.edu/ht/data/61549710/webpage","_score":1.7568384,"_source":{"description":["Hey fellas , my name Bianca . I'm a 19 year old Cali girl with a winning personality . My pictures are 100% real and  I take very good care of my body and hygiene . My smile is garaunteed to make you smile . I'll promise to keep you satisfied and keep you coming back for more ? 925-698-6375\\n"]}},{"_index":"dig-ht-california-ads-trial01-optimized","_type":"webpage","_id":"http://dig.isi.edu/ht/data/62265039/webpage","_score":1.7568384,"_source":{"description":["Hey fellas , my name is Bianca.  I am a beautiful, slim-thick, Cali girl. I have good hygiene and my pictures are 100% real. I promise to make your satisfaction my number one priority. So call me babe ,I promise you'll leave still thinking about me ? (925)698-6375\\n"]}},{"_index":"dig-ht-california-ads-trial01-optimized","_type":"webpage","_id":"http://dig.isi.edu/ht/data/69338425/webpage","_score":1.7540562,"_source":{"description":["NEW!!!Forget fake pictures ?and being rushed? !! Call\\u260e now promise to give u good time and treat u like u deserve !! I'm Real Woman ??? with a sexy attitude upcale, respectful discreet gentleman! ? I offer a non-rushed session??\\u260e(818)855-3662 bianca and you won't be Disappointed.??? VEN Y DISFRUTA DE MI COMPANIA Y DE MI LENCERIA SIEMPRE SEXY TU YA ME CONOCES NO TARDES MUCHO me gustan los chicos malos¡???\\u260e(818)855-3662 bianca????\\n"]}},{"_index":"dig-ht-california-ads-trial01-optimized","_type":"webpage","_id":"http://dig.isi.edu/ht/data/68941217/webpage","_score":1.7535951,"_source":{"description":["10am-11PM<br>\\n<br>\\n160hour,  120 half hour<br>\\n<br>\\n If you haven't seecn Bianca  You don't know what is love.<br>\\nis excellent worker Kiss, Hugs and a lots more<br>\\n Call Sexy PO 408-990-5954\\n"]}},{"_index":"dig-ht-california-ads-trial01-optimized","_type":"webpage","_id":"http://dig.isi.edu/ht/data/61912146/webpage","_score":1.7535951,"_source":{"description":["Hey fellas , my name is Bianca.  I am a beautiful, slim-thick, Cali girl. I have good hygiene and my pictures are 100% real. I promise to make your satisfaction my number one priority. So call me babe ,I promise you'll leave still thinking about me ? (925)698-6375\\n"]}},{"_index":"dig-ht-california-ads-trial01-optimized","_type":"webpage","_id":"http://dig.isi.edu/ht/data/77135469/webpage","_score":1.7535951,"_source":{"description":["10am-11PM<br>\\n<br>\\n160hour, 120 half hour<br>\\n<br>\\nIf you haven't seen Bianca You don't know what is love.<br>\\nShe is excellent worker Kiss, Hugs and a lots more<br>\\nCall Sexy PO 669-234-9637 <br>\\n<br>\\n<br>\\nLocation: ELAN VILLAGE\\n"]}},{"_index":"dig-ht-california-ads-trial01-optimized","_type":"webpage","_id":"http://dig.isi.edu/ht/data/76094555/webpage","_score":1.7535093,"_source":{"description":["10am-11PM<br>\\n<br>\\n160hour, 120 half hour<br>\\n<br>\\nIf you haven't seen Bianca You don't know what is love.<br>\\nShe is excellent worker Kiss, Hugs and a lots more<br>\\nCall Sexy PO 669-234-9637 <br>\\n<br>\\n<br>\\nLocation: ELAN VILLAGE\\n"]}},{"_index":"dig-ht-california-ads-trial01-optimized","_type":"webpage","_id":"http://dig.isi.edu/ht/data/77135477/webpage","_score":1.7535093,"_source":{"description":["10am-11PM<br>\\n<br>\\n160hour, 120 half hour<br>\\n<br>\\nIf you haven't seen Bianca You don't know what is love.<br>\\nShe is excellent worker Kiss, Hugs and a lots more<br>\\nCall Sexy PO 669-234-9637 <br>\\n<br>\\n<br>\\nLocation: ELAN VILLAGE\\n"]}},{"_index":"dig-ht-california-ads-trial01-optimized","_type":"webpage","_id":"http://dig.isi.edu/ht/data/77595547/webpage","_score":1.7535093,"_source":{"description":["10am-11PM<br>\\n<br>\\n160hour, 120 half hour<br>\\n<br>\\nIf you haven't seen Bianca You don't know what is love.<br>\\nShe is excellent worker Kiss, Hugs and a lots more<br>\\nCall Sexy PO 669-234-9637 <br>\\n<br>\\n<br>\\nLocation: ELAN VILLAGE\\n"]}},{"_index":"dig-ht-california-ads-trial01-optimized","_type":"webpage","_id":"http://dig.isi.edu/ht/data/76094547/webpage","_score":1.7518047,"_source":{"description":["10am-11PM<br>\\n<br>\\n160hour, 120 half hour<br>\\n<br>\\nIf you haven't seen Bianca You don't know what is love.<br>\\nShe is excellent worker Kiss, Hugs and a lots more<br>\\nCall Sexy PO 669-234-9637 <br>\\n<br>\\n<br>\\nLocation: ELAN VILLAGE\\n"]}},{"_index":"dig-ht-california-ads-trial01-optimized","_type":"webpage","_id":"http://dig.isi.edu/ht/data/76358459/webpage","_score":1.7515254,"_source":{"description":["10am-11PM<br>\\n<br>\\n160hour, 120 half hour<br>\\n<br>\\nIf you haven't seen Bianca You don't know what is love.<br>\\nShe is excellent worker Kiss, Hugs and a lots more<br>\\nCall Sexy PO 4154105155<br>\\n<br>\\n<br>\\nLocation: ELAN VILLAGE\\n"]}},{"_index":"dig-ht-california-ads-trial01-optimized","_type":"webpage","_id":"http://dig.isi.edu/ht/data/76009603/webpage","_score":1.7515254,"_source":{"description":["10am-11PM<br>\\n<br>\\n160hour, 120 half hour<br>\\n<br>\\nIf you haven't seen Bianca You don't know what is love.<br>\\nShe is excellent worker Kiss, Hugs and a lots more<br>\\nCall Sexy PO 669-234-9637 <br>\\n<br>\\n<br>\\nLocation: ELAN VILLAGE\\n"]}},{"_index":"dig-ht-california-ads-trial01-optimized","_type":"webpage","_id":"http://dig.isi.edu/ht/data/65541100/webpage","_score":1.7514557,"_source":{"description":["two naughty girls looking to have some fun and make your night become a fantasy!  Come and spend some time with either Jessica or Bianca! Bianca does the most and will leave you wanting to comeback for more! Jessica's No rush looooong visit will leave you completely satisfied so pick and choose!! Call us!! We will be waiting !! ask about our back \\ufe0fentrance specials and the pear back as well\\n"]}},{"_index":"dig-ht-california-ads-trial01-optimized","_type":"webpage","_id":"http://dig.isi.edu/ht/data/78968007/webpage","_score":1.751388,"_source":{"description":["10am-11PM<br>\\n<br>\\n160hour, 120 half hour<br>\\n<br>\\nIf you haven't seen Bianca You don't know what is love.<br>\\nShe is excellent worker Kiss, Hugs and a lots more<br>\\nCall Sexy PO 669-234-9637 <br>\\n<br>\\n<br>\\nLocation: ELAN VILLAGE\\n"]}},{"_index":"dig-ht-california-ads-trial01-optimized","_type":"webpage","_id":"http://dig.isi.edu/ht/data/77731080/webpage","_score":1.7479426,"_source":{"description":["10am-11PM<br>\\n<br>\\n160hour, 120 half hour<br>\\n<br>\\nIf you haven't seen Bianca You don't know what is love.<br>\\nShe is excellent worker Kiss, Hugs and a lots more<br>\\nCall Sexy PO 669-234-9637 <br>\\n<br>\\n<br>\\nLocation: ELAN VILLAGE\\n"]}},{"_index":"dig-ht-california-ads-trial01-optimized","_type":"webpage","_id":"http://dig.isi.edu/ht/data/61349424/webpage","_score":1.7479426,"_source":{"description":["Hey fellas , my name Bianca . I'm a 19 year old Cali girl with a winning personality . My pictures are 100% real and  I take very good care of my body and hygiene . My smile is garaunteed to make you smile . I'll promise to keep you satisfied and keep you coming back for more ? 925-698-6375\\n"]}},{"_index":"dig-ht-california-ads-trial01-optimized","_type":"webpage","_id":"http://dig.isi.edu/ht/data/76358461/webpage","_score":1.7438675,"_source":{"description":["10am-11PM<br>\\n<br>\\n160hour, 120 half hour<br>\\n<br>\\nIf you haven't seen Bianca You don't know what is love.<br>\\nShe is excellent worker Kiss, Hugs and a lots more<br>\\nCall Sexy PO 4154105155<br>\\n<br>\\n<br>\\nLocation: ELAN VILLAGE\\n"]}},{"_index":"dig-ht-california-ads-trial01-optimized","_type":"webpage","_id":"http://dig.isi.edu/ht/data/77595562/webpage","_score":1.7438675,"_source":{"description":["10am-11PM<br>\\n<br>\\n160hour, 120 half hour<br>\\n<br>\\nIf you haven't seen Bianca You don't know what is love.<br>\\nShe is excellent worker Kiss, Hugs and a lots more<br>\\nCall Sexy PO 669-234-9637 <br>\\n<br>\\n<br>\\nLocation: ELAN VILLAGE\\n"]}},{"_index":"dig-ht-california-ads-trial01-optimized","_type":"webpage","_id":"http://dig.isi.edu/ht/data/76009604/webpage","_score":1.7438675,"_source":{"description":["10am-11PM<br>\\n<br>\\n160hour, 120 half hour<br>\\n<br>\\nIf you haven't seen Bianca You don't know what is love.<br>\\nShe is excellent worker Kiss, Hugs and a lots more<br>\\nCall Sexy PO 669-234-9637 <br>\\n<br>\\n<br>\\nLocation: ELAN VILLAGE\\n"]}},{"_index":"dig-ht-california-ads-trial01-optimized","_type":"webpage","_id":"http://dig.isi.edu/ht/data/76358464/webpage","_score":1.7396781,"_source":{"description":["10am-11PM<br>\\n<br>\\n160hour, 120 half hour<br>\\n<br>\\nIf you haven't seen Bianca You don't know what is love.<br>\\nShe is excellent worker Kiss, Hugs and a lots more<br>\\nCall Sexy PO 4154105155<br>\\n<br>\\n<br>\\nLocation: ELAN VILLAGE\\n"]}},{"_index":"dig-ht-california-ads-trial01-optimized","_type":"webpage","_id":"http://dig.isi.edu/ht/data/76292592/webpage","_score":1.7383534,"_source":{"description":["10am-11PM<br>\\n<br>\\n160hour, 120 half hour<br>\\n<br>\\nIf you haven't seen Bianca You don't know what is love.<br>\\nShe is excellent worker Kiss, Hugs and a lots more<br>\\nCall Sexy PO 669-234-9637 <br>\\n<br>\\n<br>\\nLocation: ELAN VILLAGE\\n"]}},{"_index":"dig-ht-california-ads-trial01-optimized","_type":"webpage","_id":"http://dig.isi.edu/ht/data/77729893/webpage","_score":1.7383534,"_source":{"description":["10am-11PM<br>\\n<br>\\n160hour, 120 half hour<br>\\n<br>\\nIf you haven't seen Bianca You don't know what is love.<br>\\nShe is excellent worker Kiss, Hugs and a lots more<br>\\nCall Sexy PO 669-234-9637 <br>\\n<br>\\n<br>\\nLocation: ELAN VILLAGE\\n"]}},{"_index":"dig-ht-california-ads-trial01-optimized","_type":"webpage","_id":"http://dig.isi.edu/ht/data/50994064/webpage","_score":1.7334244,"_source":{"description":["Hello world. World Ag Expo visitors. Bianca AKA Fuchsia Phoenixx Masseuse here, offering delightfully delicious massage sessions. Please reach me, no blocked calls accepted at (559)667-1822. Availability late Tuesday evening, Wednesday and Thursday, Tulare, Visalia and Fresno areas. Best to call and verify appointment times. Thank you. Ciao, looking forward to seeing you. Bianca.\\n"]}},{"_index":"dig-ht-california-ads-trial01-optimized","_type":"webpage","_id":"http://dig.isi.edu/ht/data/50980924/webpage","_score":1.7300144,"_source":{"description":["Hello world. World Ag Expo visitors. Bianca AKA Fuchsia Phoenixx Masseuse here, offering delightfully delicious massage sessions. Please reach me, no blocked calls accepted at (559)667-1822. Availability late Tuesday evening, Wednesday and Thursday, Tulare, Visalia and Fresno areas. Best to call and verify appointment times. Thank you. Ciao, looking forward to seeing you. Bianca.\\n"]}},{"_index":"dig-ht-california-ads-trial01-optimized","_type":"webpage","_id":"http://dig.isi.edu/ht/data/57208243/webpage","_score":1.7218348,"_source":{"description":["My name is Bianca I am 23 years old looking for discreet clean mature gentlemen looking to be satisfied. <br>\\nI am a curvaceous Italian/Puerto Rican with a very pretty face. I am an energetic, well spoken, clean, caring lover. Contact me if interested. <br>\\n-Bianca<br>\\n-213-293-2939<br>\\n<br>\\n* All real photos.\\n-text messages preferred\\n-IN HOUSE CALLS ONLY \\n-Available April 8th beginning at 9am\\n"]}},{"_index":"dig-ht-california-ads-trial01-optimized","_type":"webpage","_id":"http://dig.isi.edu/ht/data/40896249/webpage","_score":1.6617433,"_source":{"description":["\\u2764LOVELY LATINA BIANCA\\u2764 Thick, Fun, Sweet. Your ultimate treat - 20\\n"]}},{"_index":"dig-ht-california-ads-trial01-optimized","_type":"webpage","_id":"http://dig.isi.edu/ht/data/57287618/webpage","_score":1.6617433,"_source":{"description":["LAST DAY \\u203c\\u203cCall Bianca for Ultimate Pleasure\\u203c\\u203c - 21\\n"]}}]}}